README.txt
setup.py
Products/__init__.py
Products.FCKEditorPatch.egg-info/PKG-INFO
Products.FCKEditorPatch.egg-info/SOURCES.txt
Products.FCKEditorPatch.egg-info/dependency_links.txt
Products.FCKEditorPatch.egg-info/entry_points.txt
Products.FCKEditorPatch.egg-info/namespace_packages.txt
Products.FCKEditorPatch.egg-info/not-zip-safe
Products.FCKEditorPatch.egg-info/requires.txt
Products.FCKEditorPatch.egg-info/top_level.txt
Products/FCKEditorPatch/__init__.py
Products/FCKEditorPatch/patch.py