Metadata-Version: 1.0
Name: Products.FCKEditorPatch
Version: 1.0
Summary: UNKNOWN
Home-page: http://www.sixfeetup.com
Author: Lucie Lejard
Author-email: lucie@sixfeetup.com
License: GPL
Platform: UNKNOWN
Classifier: Framework :: Plone
Classifier: Programming Language :: Python
Classifier: Topic :: Software Development :: Libraries :: Python Modules
